pymadng/__init__.py
pymadng/madp_classes.py
pymadng/madp_last.py
pymadng/madp_object.py
pymadng/madp_pymad.py
pymadng/madp_strings.py
pymadng/bin/mad_Darwin
pymadng/bin/mad_Linux
pymadng-0.8.3.dist-info/licenses/LICENSE
pymadng-0.8.3.dist-info/METADATA
pymadng-0.8.3.dist-info/WHEEL
pymadng-0.8.3.dist-info/top_level.txt
pymadng-0.8.3.dist-info/RECORD
