Metadata-Version: 2.4
Name: pymadng
Version: 0.8.3
Summary: A python interface to MAD-NG running as subprocess
Author: Joshua Gray
Project-URL: Repository, https://github.com/MethodicalAcceleratorDesign/MAD-NG.py
Project-URL: Bug Tracker, https://github.com/MethodicalAcceleratorDesign/MAD-NG.py/issues
Project-URL: MAD Source, https://github.com/MethodicalAcceleratorDesign/MAD
Project-URL: Documentation, https://pymadng.readthedocs.io/en/latest/
Classifier: Programming Language :: Python :: 3
Classifier: License :: OSI Approved :: GNU General Public License v3 (GPLv3)
Classifier: Operating System :: Unix
Classifier: Development Status :: 4 - Beta
Classifier: Natural Language :: English
Classifier: Topic :: Scientific/Engineering :: Physics
Requires-Python: >=3.7
License-File: LICENSE
Requires-Dist: numpy>=1.11.0
Provides-Extra: tfs
Requires-Dist: tfs-pandas>3.0.0; extra == "tfs"
Dynamic: license-file
